itech_serial/__init__.py
itech_serial/it6800.py
itech_serial/it8500.py
itech_serial/itech_serial.py
itech_serial-0.1.4.dist-info/LICENSE
itech_serial-0.1.4.dist-info/WHEEL
itech_serial-0.1.4.dist-info/METADATA
itech_serial-0.1.4.dist-info/RECORD
